setup.py
QuickView/DataFrameVisualizer.py
QuickView/__init__.py
QuickView.egg-info/PKG-INFO
QuickView.egg-info/SOURCES.txt
QuickView.egg-info/dependency_links.txt
QuickView.egg-info/not-zip-safe
QuickView.egg-info/requires.txt
QuickView.egg-info/top_level.txt