Metadata-Version: 1.1
Name: QuickView
Version: 0.2
Summary: QuickView gives you a quick glance at the dataset, just pass the pandas dataframe. It gives some useful summary and plots with just one line of code. All the summary that it outputs is made available through member variables. Its built using matplotlib.
Home-page: http://github.com/avannaldas/QuickView
Author: Abhijit Annaldas
Author-email: avannaldas@hotmail.com
License: MIT
Platform: UNKNOWN
Classifier: Development Status :: 4 - Beta
Classifier: Intended Audience :: Developers
Classifier: Programming Language :: Python
Classifier: Topic :: Scientific/Engineering
Classifier: Topic :: Scientific/Engineering :: Information Analysis
Classifier: Topic :: Scientific/Engineering :: Visualization
Classifier: Topic :: Software Development :: Libraries
Classifier: Topic :: Software Development :: Libraries :: Python Modules
Classifier: Topic :: Utilities
